Workbook

Sheet График
A1: PECÀN coffee & bakery · План открытия
A2: Астана, пр. Тұран, 52/4 · ведёт команда PECÀN · состояние на 18 окт 2026 · даты, проценты и ответственных можно менять, полосы справа пересчитаются сами
A4: № | B4: Этап | C4: Работа | D4: Ответственный | E4: Участвуют | F4: Начало | G4: Окончание | H4: Дней | I4: Выполнено | J4: Статус | K4: Веха | L4: Критический путь | M4: Описание и результат | N4: 46279 | O4: 46286 | P4: 46293 | Q4: 46300 | R4: 46307 | S4: 46314 | T4: 46321 | U4: 46328 | V4: 46335 | W4: 46342 | X4: 46349 | Y4: 46356 | Z4: 46363 | AA4: 46370 | AB4: 46377 | AC4: 46384 | AD4: 46391 | AE4: 46398 | AF4: 46405 | AG4: 46412 | AH4: 46419 | AI4: 46426 | AJ4: 46433 | AK4: 46440 | AL4: 46447 | AM4: 46454 | AN4: 46461
A5: 1 | B5: Старт проекта | C5: Бриф, обмерный план, айдентика и брендбук переданы | D5: Команда PECÀN | F5: 46281 | G5: 46282 | H5: =G5-F5+1 | I5: 1 | J5: =IF(I5>=1,"Готово",IF(G5<TODAY(),"Просрочено",IF(F5<=TODAY(),"В работе","В плане"))) | M5: Передача исходных материалов по проекту: заполненный бриф, обмерный план помещения 120,67 м², айдентика и брендбук. Результат: Все исходные документы лежат в общем чате, по ним можно начинать аналитику и планировку.
A6: 2 | B6: Старт проекта | C6: Договор подписан | D6: Команда PECÀN | F6: 46292 | G6: 46292 | H6: =G6-F6+1 | I6: 1 | J6: =IF(I6>=1,"Готово",IF(G6<TODAY(),"Просрочено",IF(F6<=TODAY(),"В работе","В плане"))) | K6: да | M6: Подписание договора на сопровождение открытия кофейни-пекарни. С этой даты идёт отсчёт всех работ. Результат: Договор подписан обеими сторонами, у каждой стороны свой экземпляр.
A7: 3 | B7: Старт проекта | C7: Календарный план проекта | D7: Команда PECÀN | F7: 46293 | G7: 46300 | H7: =G7-F7+1 | I7: 1 | J7: =IF(I7>=1,"Готово",IF(G7<TODAY(),"Просрочено",IF(F7<=TODAY(),"В работе","В плане"))) | M7: Собираем все работы проекта в один график: что делаем, в какие сроки, кто отвечает, какие даты ключевые. По нему дальше отчитываемся на еженедельных созвонах. Результат: График согласован и закреплён в общем чате, все участники знают свои сроки.
A8: 4 | B8: Старт проекта | C8: Регистрация ТОО, расчётный счёт, ОКЭД 56101 | D8: Команда PECÀN | F8: 46314 | G8: 46325 | H8: =G8-F8+1 | I8: 0 | J8: =IF(I8>=1,"Готово",IF(G8<TODAY(),"Просрочено",IF(F8<=TODAY(),"В работе","В плане"))) | M8: Регистрация ТОО на двух учредителей и открытие расчётного счёта. Основной ОКЭД 56101, режим упрощённой декларации выбирается сразу при регистрации. Юрлицо нужно для договоров с подрядчиками, поставщиками, ЖКХ и для импорта оборудования. Результат: ТОО зарегистрировано, счёт открыт, реквизиты переданы в общий чат.
A9: 5 | B9: Аналитика и стратегия | C9: Анализ конкурентов района Туран | D9: Команда PECÀN | F9: 46293 | G9: 46304 | H9: =G9-F9+1 | I9: 1 | J9: =IF(I9>=1,"Готово",IF(G9<TODAY(),"Просрочено",IF(F9<=TODAY(),"В работе","В плане"))) | M9: Обходим и изучаем кофейни и пекарни в радиусе района: меню, цены, средний чек, загрузку по времени, сильные и слабые стороны. Смотрим, чего району не хватает. Результат: Сводная таблица конкурентов и вывод: в чём PECÀN будет отличаться и какой средний чек закладывать.
A10: 6 | B10: Аналитика и стратегия | C10: Замер трафика у входа и оценка потока гостей | D10: Команда PECÀN | F10: 46293 | G10: 46305 | H10: =G10-F10+1 | I10: 1 | J10: =IF(I10>=1,"Готово",IF(G10<TODAY(),"Просрочено",IF(F10<=TODAY(),"В работе","В плане"))) | M10: Провели натурные замеры у входа 3–7 октября: пять сессий в будни и выходные, утро, обед и вечер. Считали пешеходов вдоль фасада и по аллее, автомобили на кольцевом проезде. Данные сверили с расчётной моделью квартала и получили ожидаемое число чеков в день. Результат: Отчёт по замеру трафика и раздел «Локация, трафик и ожидаемый поток гостей» в общем отчёте с анализом конкурентов: поток по дням и часам, расчёт числа чеков.
A11: 7 | B11: Аналитика и стратегия | C11: Маркетинговая стратегия и ассортиментная матрица | D11: Команда PECÀN | F11: 46300 | G11: 46313 | H11: =G11-F11+1 | I11: 1 | J11: =IF(I11>=1,"Готово",IF(G11<TODAY(),"Просрочено",IF(F11<=TODAY(),"В работе","В плане"))) | M11: Формулируем, для кого PECÀN и чем он запоминается, собираем ассортиментную матрицу: категории, ценовые уровни, хиты. Продумываем механики привлечения соседей и программу лояльности. Результат: Документ со стратегией запуска и ассортиментной матрицей, с которой можно идти к шефам за меню.
A12: 8 | B12: Аналитика и стратегия | C12: Финансовая модель: CAPEX, OPEX, P&L, Cash Flow | D12: Команда PECÀN | F12: 46300 | G12: 46313 | H12: =G12-F12+1 | I12: 1 | J12: =IF(I12>=1,"Готово",IF(G12<TODAY(),"Просрочено",IF(F12<=TODAY(),"В работе","В плане"))) | M12: Считаем экономику проекта: сколько нужно вложить (CAPEX), ежемесячные расходы (OPEX), прогноз прибыли и убытков, движение денег по месяцам. Цифры опираются на замер трафика, анализ конкурентов и меню: цену и себестоимость каждой позиции; якорные позиции стоят на уровне сетей, уникальные — по ценности продукта. Результат: Модель в Excel с точкой безубыточности, сроком окупаемости и бюджетом открытия, который укладывается в ваш лимит.
A13: 9 | B13: Аналитика и стратегия | C13: Защита финмодели и бюджета | D13: Команда PECÀN | F13: 46315 | G13: 46315 | H13: =G13-F13+1 | I13: 0 | J13: =IF(I13>=1,"Готово",IF(G13<TODAY(),"Просрочено",IF(F13<=TODAY(),"В работе","В плане"))) | K13: да | M13: Встреча, на которой проходим финансовую модель и бюджет открытия: откуда каждая цифра и где можно сэкономить. Результат: Бюджет открытия утверждён, вопросов по цифрам не осталось.
A14: 10 | B14: Технологический проект | C14: Технологическое зонирование: варианты планировки | D14: Команда PECÀN | F14: 46293 | G14: 46304 | H14: =G14-F14+1 | I14: 1 | J14: =IF(I14>=1,"Готово",IF(G14<TODAY(),"Просрочено",IF(F14<=TODAY(),"В работе","В плане"))) | L14: да | M14: Раскладываем 120 м² на зоны: зал на 31 место, бар с витриной, пекарня, заготовочная, мойка, склад, санузлы. Готовим несколько вариантов и проверяем, чтобы потоки гостей, продуктов и грязной посуды не пересекались. Оцениваем антресоль при высоте потолка 4,52 м. Результат: Два–три варианта планировки с плюсами и минусами каждого, готовые к выбору.
A15: 11 | B15: Технологический проект | C15: Проект ТХ: комплект чертежей по СанПиН и ХАССП | D15: Команда PECÀN | F15: 46307 | G15: 46325 | H15: =G15-F15+1 | I15: 0 | J15: =IF(I15>=1,"Готово",IF(G15<TODAY(),"Просрочено",IF(F15<=TODAY(),"В работе","В плане"))) | L15: да | M15: Технологический проект: чертежи с расстановкой всего оборудования и привязкой к коммуникациям, по нормам СанПиН и ХАССП. Это основной документ для строителей и для закупки оборудования. Результат: Комплект чертежей раздела ТХ, по которому можно строить и заказывать оборудование.
A16: 12 | B16: Технологический проект | C16: Зонирование согласовано | D16: Команда PECÀN | F16: 46313 | G16: 46313 | H16: =G16-F16+1 | I16: 1 | J16: =IF(I16>=1,"Готово",IF(G16<TODAY(),"Просрочено",IF(F16<=TODAY(),"В работе","В плане"))) | K16: да | L16: да | M16: Выбор одного варианта планировки из предложенных. От него зависят проект ТХ, дизайн и работа строителей. Результат: Проект зонирования подтверждён: планировка, перегородки и двери, мебель и оборудование, антресоль, потоки. Дальше работаем только по нему.
A17: 13 | B17: Технологический проект | C17: Задание на инженерные сети: точки подключения и нагрузки оборудования | D17: Команда PECÀN | F17: 46314 | G17: 46325 | H17: =G17-F17+1 | I17: 0 | J17: =IF(I17>=1,"Готово",IF(G17<TODAY(),"Просрочено",IF(F17<=TODAY(),"В работе","В плане"))) | M17: Команда PECÀN описывает, что нужно оборудованию: где какая розетка и какой мощности, включая 380 В для печей, где подвести воду и канализацию, где поставить трапы, какая вытяжка нужна над печами и плитой. Это задание для инженеров бригады: сами схемы и расчёты кабелей, труб и воздуховодов делают они. Результат: Задание по электрике, воде, канализации и вентиляции, по которому бригада делает рабочие схемы и считает смету.
A18: 14 | B18: Технологический проект | C18: Раздел ТХ и задание на инженерные сети сданы | D18: Команда PECÀN | F18: 46328 | G18: 46328 | H18: =G18-F18+1 | I18: 0 | J18: =IF(I18>=1,"Готово",IF(G18<TODAY(),"Просрочено",IF(F18<=TODAY(),"В работе","В плане"))) | K18: да | M18: Передача готового раздела ТХ и задания на инженерные сети. С этого момента строители могут выходить на объект и делать рабочие схемы. Результат: Чертежи и задание переданы, замечаний нет.
A19: 15 | B19: Дизайн-проект | C19: Концепция интерьера и планировочное решение | D19: Команда PECÀN | F19: 46314 | G19: 46325 | H19: =G19-F19+1 | I19: 0.6 | J19: =IF(I19>=1,"Готово",IF(G19<TODAY(),"Просрочено",IF(F19<=TODAY(),"В работе","В плане"))) | L19: да | M19: Команда PECÀN разрабатывает образ интерьера: настроение, материалы, цвета, свет, расстановку мебели — по брендбуку, референсам и утверждённому зонированию. Варианты концепции подготовлены, выбираем один. Результат: Концепция и планировочное решение согласованы, можно делать визуализации.
A20: 16 | B20: Дизайн-проект | C20: Подбор подрядчиков на точечные услуги по дизайну | D20: Команда PECÀN | F20: 46314 | G20: 46325 | H20: =G20-F20+1 | I20: 0 | J20: =IF(I20>=1,"Готово",IF(G20<TODAY(),"Просрочено",IF(F20<=TODAY(),"В работе","В плане"))) | L20: да | M20: Концепцию интерьера и 3D-визуализации команда PECÀN делает сама. Подрядчиков привлекаем точечно — там, где нужна отдельная специализация: рабочие чертежи и ведомости для строителей, план освещения и розеток, эскиз вывески, авторский надзор. По каждой услуге запрашиваем предложения у двух–трёх исполнителей с опытом в кофейнях и пекарнях. Результат: Исполнители по каждой услуге выбраны, сроки и стоимость сравнены.
A21: 17 | B21: Дизайн-проект | C21: 3D-визуализации интерьера | D21: Команда PECÀN | F21: 46321 | G21: 46332 | H21: =G21-F21+1 | I21: 0.3 | J21: =IF(I21>=1,"Готово",IF(G21<TODAY(),"Просрочено",IF(F21<=TODAY(),"В работе","В плане"))) | L21: да | M21: Реалистичные картинки будущего интерьера с основных ракурсов: вход, бар и витрина, зал, санузел. Сцена строится по геометрии проекта зонирования; для части вариантов концепции визуализации уже есть, для выбранного варианта делаем полный набор. Результат: Визуализации согласованы: вы видите, как будет выглядеть кофейня, и вам это нравится.
A22: 18 | B22: Дизайн-проект | C22: Договоры на услуги по дизайну подписаны | D22: Команда PECÀN | F22: 46325 | G22: 46325 | H22: =G22-F22+1 | I22: 0 | J22: =IF(I22>=1,"Готово",IF(G22<TODAY(),"Просрочено",IF(F22<=TODAY(),"В работе","В плане"))) | K22: да | L22: да | M22: Договоры с выбранными исполнителями: рабочая документация, свет и розетки, вывеска, авторский надзор. В договорах фиксируются даты сдачи и оплата по этапам. Результат: Договоры подписаны, исполнители получили проект зонирования, концепцию интерьера и брендбук и приступили к работе.
A23: 19 | B23: Дизайн-проект | C23: Сверка визуализаций с технологическим зонированием | D23: Команда PECÀN | F23: 46328 | G23: 46332 | H23: =G23-F23+1 | I23: 0 | J23: =IF(I23>=1,"Готово",IF(G23<TODAY(),"Просрочено",IF(F23<=TODAY(),"В работе","В плане"))) | M23: Проверяем, что красивый интерьер не ломает рабочие процессы: хватает ли места бариста, проходит ли поток гостей, помещается ли оборудование. Результат: Список правок либо подтверждение, что расхождений с ТХ нет.
A24: 20 | B24: Дизайн-проект | C24: Рабочая документация: чертежи, ведомости, смета | D24: Подрядчики по дизайну | F24: 46328 | G24: 46346 | H24: =G24-F24+1 | I24: 0 | J24: =IF(I24>=1,"Готово",IF(G24<TODAY(),"Просрочено",IF(F24<=TODAY(),"В работе","В плане"))) | L24: да | M24: Рабочие чертежи для строителей, план освещения, план розеток и выключателей в зале, ведомости отделки, мебели и освещения, проектная смета. Выполняет подрядчик по выбранной концепции команды PECÀN. Срок сжатый: три недели от договора до полного комплекта. Результат: Полный комплект документации, по которому строители работают без вопросов, а мы собираем закупочные спецификации. Как снижаем риск: В договоре с подрядчиком закрепить дату сдачи рабочей документации — 20 ноября, оплата по этапам.; Выбирать исполнителя с готовой командой чертёжников. Спросить о текущей загрузке.; В первый день передать проект зонирования, выбранную концепцию интерьера и брендбук.; Ведомости мебели, света и отделки получить первыми, к 13 ноября: они нужны для поездки в Китай.; Согласовывать материалы за 1–2 дня, а не за 3.; Строители выходят 2 ноября по проекту ТХ и не ждут дизайн.
A25: 21 | B25: Дизайн-проект | C25: Авторский надзор дизайнера: выезды на объект, контроль отделки | D25: Подрядчики по дизайну | E25: Строители | F25: 46328 | G25: 46427 | H25: =G25-F25+1 | I25: 0 | J25: =IF(I25>=1,"Готово",IF(G25<TODAY(),"Просрочено",IF(F25<=TODAY(),"В работе","В плане"))) | M25: Дизайнер регулярно приезжает на объект, пока идут отделка и монтаж: проверяет соответствие проекту, согласует замены материалов, отвечает на вопросы бригады. Входит в договор с подрядчиком. Результат: Интерьер построен так, как на визуализациях, отступления от проекта согласованы заранее.
A26: 22 | B26: Дизайн-проект | C26: Вывеска: эскиз, согласование, изготовление, монтаж | D26: Команда PECÀN | E26: Подрядчики по дизайну | F26: 46335 | G26: 46409 | H26: =G26-F26+1 | I26: 0 | J26: =IF(I26>=1,"Готово",IF(G26<TODAY(),"Просрочено",IF(F26<=TODAY(),"В работе","В плане"))) | M26: Фасадная вывеска по брендбуку: эскиз, согласование размещения, изготовление и монтаж. Результат: Вывеска висит на фасаде и подсвечивается, размещение согласовано.
A27: 23 | B27: Дизайн-проект | C27: Дизайн-проект готов полностью | D27: Команда PECÀN | F27: 46346 | G27: 46346 | H27: =G27-F27+1 | I27: 0 | J27: =IF(I27>=1,"Готово",IF(G27<TODAY(),"Просрочено",IF(F27<=TODAY(),"В работе","В плане"))) | K27: да | L27: да | M27: Сдача всего дизайн-проекта: концепция, визуализации, рабочая документация. Он должен быть готов до поездки в Китай, потому что по нему закупаются мебель и свет. Результат: Проект принят целиком, правок не осталось.
A28: 24 | B28: Дизайн-проект | C28: Интерьер принят дизайнером по проекту | D28: Подрядчики по дизайну | F28: 46427 | G28: 46427 | H28: =G28-F28+1 | I28: 0 | J28: =IF(I28>=1,"Готово",IF(G28<TODAY(),"Просрочено",IF(F28<=TODAY(),"В работе","В плане"))) | K28: да | M28: Финальный обход помещения с дизайнером после расстановки мебели и декора. Результат: Дизайнер подтверждает, что интерьер соответствует проекту, список мелких доделок закрыт.
A29: 25 | B29: Строительство и отделка | C29: Поиск строительной бригады: кандидаты, объекты, отзывы | D29: Команда PECÀN | F29: 46300 | G29: 46316 | H29: =G29-F29+1 | I29: 0 | J29: =IF(I29>=1,"Готово",IF(G29<TODAY(),"Просрочено",IF(F29<=TODAY(),"В работе","В плане"))) | L29: да | M29: Ищем строительную бригаду с нуля. Отбираем тех, кто уже делал заведения общепита: электрика 380 В, вентиляция, мокрые зоны. Обязательное условие: у бригады есть свой инженер, который делает рабочие схемы сетей с расчётами. Выезжаем на сданные объекты и звоним прошлым клиентам. Результат: Три–четыре проверенные бригады, готовые дать смету.
A30: 26 | B30: Строительство и отделка | C30: Сметы от бригад и сравнение предложений | D30: Команда PECÀN | F30: 46317 | G30: 46323 | H30: =G30-F30+1 | I30: 0 | J30: =IF(I30>=1,"Готово",IF(G30<TODAY(),"Просрочено",IF(F30<=TODAY(),"В работе","В плане"))) | L30: да | M30: Бригады считают сметы по нашему зонированию и заданию на инженерные сети. Сравниваем цены, сроки, условия оплаты и гарантии, проверяем, что в сметах нет завышенных объёмов. Результат: Сравнительная таблица смет и рекомендация, какую бригаду брать.
A31: 27 | B31: Строительство и отделка | C31: Договор подряда подписан | D31: Команда PECÀN | E31: Строители | F31: 46325 | G31: 46325 | H31: =G31-F31+1 | I31: 0 | J31: =IF(I31>=1,"Готово",IF(G31<TODAY(),"Просрочено",IF(F31<=TODAY(),"В работе","В плане"))) | K31: да | L31: да | M31: Подписание договора подряда с выбранной бригадой. В договоре: сроки по этому графику, поэтапная оплата, закупка материалов по проектной смете. Результат: Договор подписан, бригада подтверждает выход на объект 2 ноября.
A32: 28 | B32: Строительство и отделка | C32: Строители вышли на объект | D32: Строители | F32: 46328 | G32: 46328 | H32: =G32-F32+1 | I32: 0 | J32: =IF(I32>=1,"Готово",IF(G32<TODAY(),"Просрочено",IF(F32<=TODAY(),"В работе","В плане"))) | K32: да | M32: Начало ремонта: бригада заходит на объект с материалами и инструментом. Результат: Работы на объекте начаты в срок.
A33: 29 | B33: Строительство и отделка | C33: Рабочие схемы электрики, воды и вентиляции с расчётами | D33: Строители | E33: Команда PECÀN: проверка | F33: 46328 | G33: 46332 | H33: =G33-F33+1 | I33: 0 | J33: =IF(I33>=1,"Готово",IF(G33<TODAY(),"Просрочено",IF(F33<=TODAY(),"В работе","В плане"))) | M33: Инженер бригады по нашему заданию делает рабочие схемы: щит и автоматы, сечения кабелей, трассы труб, диаметры, воздуховоды и подбор вентиляторов. Розетки и свет в зале берёт из дизайн-проекта. Схемы готовы до начала прокладки сетей. Результат: Схемы электрики, водоснабжения, канализации и вентиляции проверены командой PECÀN, по ним уточнена смета.
A34: 30 | B34: Строительство и отделка | C34: Черновые работы и перегородки | D34: Строители | F34: 46328 | G34: 46346 | H34: =G34-F34+1 | I34: 0 | J34: =IF(I34>=1,"Готово",IF(G34<TODAY(),"Просрочено",IF(F34<=TODAY(),"В работе","В плане"))) | M34: Разметка помещения по проекту, возведение перегородок, подготовка стен и пола под инженерные сети. Результат: Помещение разделено на зоны по планировке, перегородки стоят.
A35: 31 | B35: Строительство и отделка | C35: Электрика, вода, канализация, трапы, жироуловитель | D35: Строители | F35: 46335 | G35: 46360 | H35: =G35-F35+1 | I35: 0 | J35: =IF(I35>=1,"Готово",IF(G35<TODAY(),"Просрочено",IF(F35<=TODAY(),"В работе","В плане"))) | M35: Прокладка электрики с выводом 380 В под печи, водопровода, канализации, установка трапов и жироуловителя. Работы идут по рабочим схемам бригады, которые сделаны по заданию команды PECÀN. Результат: Все выводы сделаны в точках по проекту и проверены до закрытия стен.
A36: 32 | B36: Строительство и отделка | C36: Технологический надзор за выводами коммуникаций | D36: Команда PECÀN | F36: 46335 | G36: 46367 | H36: =G36-F36+1 | I36: 0 | J36: =IF(I36>=1,"Готово",IF(G36<TODAY(),"Просрочено",IF(F36<=TODAY(),"В работе","В плане"))) | M36: Команда PECÀN выезжает на объект и проверяет, что розетки, вода, канализация и вытяжка выведены ровно там, где будет стоять оборудование, и соответствуют заданию. Результат: Акты осмотра подписаны до закрытия стен, переделок после отделки не потребуется.
A37: 33 | B37: Строительство и отделка | C37: Вентиляция и кондиционирование | D37: Строители | F37: 46342 | G37: 46367 | H37: =G37-F37+1 | I37: 0 | J37: =IF(I37>=1,"Готово",IF(G37<TODAY(),"Просрочено",IF(F37<=TODAY(),"В работе","В плане"))) | M37: Монтаж вытяжки над пекарней и кухней, приточной вентиляции и кондиционеров в зале. Результат: Вентиляция работает, в зале нет запахов кухни, кондиционеры охлаждают и греют.
A38: 34 | B38: Строительство и отделка | C38: Чистовая отделка | D38: Строители | F38: 46363 | G38: 46402 | H38: =G38-F38+1 | I38: 0 | J38: =IF(I38>=1,"Готово",IF(G38<TODAY(),"Просрочено",IF(F38<=TODAY(),"В работе","В плане"))) | M38: Финишная отделка стен, пола и потолка по дизайн-проекту: штукатурка, покраска, плитка, напольное покрытие. Результат: Отделка завершена и принята дизайнером, помещение выглядит как на визуализациях.
A39: 35 | B39: Строительство и отделка | C39: Свет, сантехника, столярные изделия | D39: Строители | F39: 46391 | G39: 46409 | H39: =G39-F39+1 | I39: 0 | J39: =IF(I39>=1,"Готово",IF(G39<TODAY(),"Просрочено",IF(F39<=TODAY(),"В работе","В плане"))) | M39: Установка светильников, сантехники, барной стойки и встроенной мебели. Результат: Свет горит, вода течёт, стойка и встроенная мебель стоят на местах.
A40: 36 | B40: Строительство и отделка | C40: Приёмка строительной готовности | D40: Команда PECÀN | E40: Строители | F40: 46412 | G40: 46412 | H40: =G40-F40+1 | I40: 0 | J40: =IF(I40>=1,"Готово",IF(G40<TODAY(),"Просрочено",IF(F40<=TODAY(),"В работе","В плане"))) | K40: да | M40: Совместный обход помещения после ремонта: команда PECÀN, строители, дизайнер. Проверяем качество работ и готовность принять оборудование. Результат: Акт приёмки подписан, замечания устранены, помещение готово к завозу оборудования.
A41: 37 | B41: Строительство и отделка | C41: Генеральная уборка после ремонта | D41: Строители | F41: 46412 | G41: 46414 | H41: =G41-F41+1 | I41: 0 | J41: =IF(I41>=1,"Готово",IF(G41<TODAY(),"Просрочено",IF(F41<=TODAY(),"В работе","В плане"))) | M41: Профессиональная уборка после строителей: пыль, следы краски, мытьё окон и полов. Результат: Помещение чистое, можно завозить оборудование и мебель.
A42: 38 | B42: Комплектация и Китай | C42: Спецификации технологического оборудования и инвентаря | D42: Команда PECÀN | F42: 46321 | G42: 46339 | H42: =G42-F42+1 | I42: 0 | J42: =IF(I42>=1,"Готово",IF(G42<TODAY(),"Просрочено",IF(F42<=TODAY(),"В работе","В плане"))) | L42: да | M42: Составляем точный список техники и инвентаря по проекту ТХ: печи, расстойка, холод, бар, нейтральное оборудование. Для каждой позиции указываем модель, размеры, мощность и количество. Результат: Спецификация, с которой можно ехать на фабрики и запрашивать цены.
A43: 39 | B43: Комплектация и Китай | C43: Подготовка поездки: маршрут фабрик, визы, билеты | D43: Команда PECÀN | F43: 46328 | G43: 46346 | H43: =G43-F43+1 | I43: 0 | J43: =IF(I43>=1,"Готово",IF(G43<TODAY(),"Просрочено",IF(F43<=TODAY(),"В работе","В плане"))) | M43: Готовим поездку: договариваемся с фабриками в Гуанчжоу и Фошане, составляем маршрут по дням, оформляем визы и покупаем билеты. Результат: Маршрут с адресами и временем встреч, визы и билеты на руках.
A44: 40 | B44: Комплектация и Китай | C44: Спецификации мебели, света и посуды по дизайн-проекту | D44: Команда PECÀN | E44: Подрядчики по дизайну | F44: 46335 | G44: 46346 | H44: =G44-F44+1 | I44: 0 | J44: =IF(I44>=1,"Готово",IF(G44<TODAY(),"Просрочено",IF(F44<=TODAY(),"В работе","В плане"))) | L44: да | M44: Список мебели, светильников и посуды по ведомостям из дизайн-проекта: размеры, материалы, цвета, количество. Результат: Спецификация, по которой фабрики дают цены и сроки.
A45: 41 | B45: Комплектация и Китай | C45: Спецификации и бюджет закупок утверждены | D45: Команда PECÀN | F45: 46346 | G45: 46346 | H45: =G45-F45+1 | I45: 0 | J45: =IF(I45>=1,"Готово",IF(G45<TODAY(),"Просрочено",IF(F45<=TODAY(),"В работе","В плане"))) | K45: да | L45: да | M45: Утверждение списка закупок и суммы, которую готовы на них потратить. Результат: Спецификации и бюджет закупок письменно подтверждены.
A46: 42 | B46: Комплектация и Китай | C46: Выездная сессия в Китае: Гуанчжоу, Фошань | D46: Команда PECÀN | F46: 46349 | G46: 46355 | H46: =G46-F46+1 | I46: 0 | J46: =IF(I46>=1,"Готово",IF(G46<TODAY(),"Просрочено",IF(F46<=TODAY(),"В работе","В плане"))) | L46: да | M46: Неделя на фабриках и в шоурумах: смотрим оборудование, мебель, свет и посуду вживую, проверяем качество, торгуемся и согласуем сроки изготовления. Результат: По каждой позиции выбран поставщик, согласованы цена и срок готовности.
A47: 43 | B47: Комплектация и Китай | C47: Размещение заказов и предоплата фабрикам | D47: Команда PECÀN | F47: 46356 | G47: 46360 | H47: =G47-F47+1 | I47: 0 | J47: =IF(I47>=1,"Готово",IF(G47<TODAY(),"Просрочено",IF(F47<=TODAY(),"В работе","В плане"))) | L47: да | M47: Подписываем контракты с фабриками и вносим предоплату. Чем раньше оплата, тем раньше фабрика запускает производство. Результат: Все заказы оплачены, фабрики подтвердили дату готовности.
A48: 44 | B48: Комплектация и Китай | C48: Заказ кофемашины у дилера в Казахстане | D48: Команда PECÀN | F48: 46356 | G48: 46367 | H48: =G48-F48+1 | I48: 0 | J48: =IF(I48>=1,"Готово",IF(G48<TODAY(),"Просрочено",IF(F48<=TODAY(),"В работе","В плане"))) | M48: Выбор и заказ кофемашины у дилера в Казахстане: с гарантией, сервисом и обучением. Результат: Кофемашина оплачена, дилер подтвердил дату поставки и установки.
A49: 45 | B49: Комплектация и Китай | C49: Производство на фабриках | D49: Поставщики и логистика | F49: 46363 | G49: 46395 | H49: =G49-F49+1 | I49: 0 | J49: =IF(I49>=1,"Готово",IF(G49<TODAY(),"Просрочено",IF(F49<=TODAY(),"В работе","В плане"))) | L49: да | M49: Фабрики изготавливают заказ. Раз в неделю получаем фото и видео, чтобы видеть ход работ и сроки. Результат: Всё изготовлено к согласованной дате и соответствует образцам.
A50: 46 | B50: Комплектация и Китай | C50: Контроль качества и отгрузка из Китая | D50: Поставщики и логистика | F50: 46391 | G50: 46400 | H50: =G50-F50+1 | I50: 0 | J50: =IF(I50>=1,"Готово",IF(G50<TODAY(),"Просрочено",IF(F50<=TODAY(),"В работе","В плане"))) | L50: да | M50: Проверяем готовый товар на фабриках перед упаковкой и отправляем. Отгрузка с запасом до закрытия фабрик на Китайский Новый год. Результат: Товар проверен, упакован и передан перевозчику до праздников. Как снижаем риск: Разместить заказы и внести предоплату в первую неделю после поездки, до 4 декабря.; В контракте с фабрикой указать дату готовности 8 января и удержание за просрочку.; Брать позиции из стандартных линеек с коротким сроком. Изготовление на заказ оставить только там, где без него нельзя.; Раз в неделю получать от фабрики фото и видео хода производства.; За неделю до готовности отправить на фабрику инспектора по качеству.
A51: 47 | B51: Комплектация и Китай | C51: Доставка и таможенное оформление | D51: Поставщики и логистика | F51: 46400 | G51: 46416 | H51: =G51-F51+1 | I51: 0 | J51: =IF(I51>=1,"Готово",IF(G51<TODAY(),"Просрочено",IF(F51<=TODAY(),"В работе","В плане"))) | L51: да | M51: Доставка груза из Китая в Астану и таможенное оформление. Везёт наша проверенная транспортная компания. Результат: Груз растаможен и готов к доставке на объект.
A52: 48 | B52: Комплектация и Китай | C52: Оборудование и мебель на объекте | D52: Поставщики и логистика | F52: 46416 | G52: 46416 | H52: =G52-F52+1 | I52: 0 | J52: =IF(I52>=1,"Готово",IF(G52<TODAY(),"Просрочено",IF(F52<=TODAY(),"В работе","В плане"))) | K52: да | L52: да | M52: Разгрузка и приёмка: пересчитываем места, проверяем целостность упаковки и комплектность. Результат: Всё заказанное на объекте, повреждений нет либо они зафиксированы актом.
A53: 49 | B53: Комплектация и Китай | C53: Монтаж оборудования, пусконаладка | D53: Поставщики и логистика | E53: Команда PECÀN: шеф-контроль | F53: 46419 | G53: 46425 | H53: =G53-F53+1 | I53: 0 | J53: =IF(I53>=1,"Готово",IF(G53<TODAY(),"Просрочено",IF(F53<=TODAY(),"В работе","В плане"))) | L53: да | M53: Расстановка оборудования по проекту ТХ, подключение к электрике, воде и вытяжке, пробный запуск каждой единицы. Результат: Вся техника работает, персонал может начинать проработки.
A54: 50 | B54: Комплектация и Китай | C54: Расстановка мебели, свет, декор | D54: Подрядчики по дизайну | F54: 46421 | G54: 46427 | H54: =G54-F54+1 | I54: 0 | J54: =IF(I54>=1,"Готово",IF(G54<TODAY(),"Просрочено",IF(F54<=TODAY(),"В работе","В плане"))) | M54: Сборка и расстановка мебели в зале, развеска светильников, декор и растения. Результат: Зал полностью обставлен и выглядит как на визуализациях.
A55: 51 | B55: Команда | C55: Штатное расписание, фонд оплаты труда, KPI | D55: Команда PECÀN | F55: 46328 | G55: 46339 | H55: =G55-F55+1 | I55: 0 | J55: =IF(I55>=1,"Готово",IF(G55<TODAY(),"Просрочено",IF(F55<=TODAY(),"В работе","В плане"))) | M55: Определяем, сколько человек и на какие должности нужно, какие смены и зарплаты, как считается премия за результат. Результат: Штатное расписание с фондом оплаты труда и понятной системой мотивации.
A56: 52 | B56: Команда | C56: Подбор шеф-пекаря и шеф-бариста | D56: Команда PECÀN | F56: 46342 | G56: 46367 | H56: =G56-F56+1 | I56: 0 | J56: =IF(I56>=1,"Готово",IF(G56<TODAY(),"Просрочено",IF(F56<=TODAY(),"В работе","В плане"))) | M56: Ищем шефов, которые разработают меню выпечки и кофейную карту PECÀN и обучат команду. Результат: С шеф-пекарем и шеф-бариста заключены договоры на разработку меню.
A57: 53 | B57: Команда | C57: Поиск управляющего | D57: Команда PECÀN | F57: 46342 | G57: 46374 | H57: =G57-F57+1 | I57: 0 | J57: =IF(I57>=1,"Готово",IF(G57<TODAY(),"Просрочено",IF(F57<=TODAY(),"В работе","В плане"))) | M57: Ищем управляющего кофейней: размещаем вакансию, приглашаем сильных кандидатов из других заведений, проводим собеседования и проверяем рекомендации. Результат: Управляющий выбран и готов выйти на обучение 25 января.
A58: 54 | B58: Команда | C58: Подбор линейного персонала | D58: Команда PECÀN | F58: 46391 | G58: 46416 | H58: =G58-F58+1 | I58: 0 | J58: =IF(I58>=1,"Готово",IF(G58<TODAY(),"Просрочено",IF(F58<=TODAY(),"В работе","В плане"))) | M58: Набор команды: бариста, пекари, повара, кассиры, сотрудники зала и клининг. Вакансии, отбор анкет, собеседования, пробные смены. Результат: На каждую должность есть утверждённый кандидат с проверенными рекомендациями.
A59: 55 | B59: Команда | C59: Оформление сотрудников и медицинские книжки | D59: Команда PECÀN | F59: 46412 | G59: 46423 | H59: =G59-F59+1 | I59: 0 | J59: =IF(I59>=1,"Готово",IF(G59<TODAY(),"Просрочено",IF(F59<=TODAY(),"В работе","В плане"))) | M59: Официальное оформление сотрудников и прохождение медосмотра с получением медицинских книжек. Результат: Со всеми подписаны договоры, у каждого действующая медкнижка.
A60: 56 | B60: Команда | C60: Штат укомплектован: 10–14 человек | D60: Команда PECÀN | F60: 46416 | G60: 46416 | H60: =G60-F60+1 | I60: 0 | J60: =IF(I60>=1,"Готово",IF(G60<TODAY(),"Просрочено",IF(F60<=TODAY(),"В работе","В плане"))) | K60: да | M60: Финальная проверка: все должности закрыты, люди подтвердили выход. Результат: Полный штат из 10–14 человек готов к обучению.
A61: 57 | B61: Меню и продукт | C61: Концепция меню | D61: Команда PECÀN | E61: Шефы | F61: 46335 | G61: 46353 | H61: =G61-F61+1 | I61: 0 | J61: =IF(I61>=1,"Готово",IF(G61<TODAY(),"Просрочено",IF(F61<=TODAY(),"В работе","В плане"))) | M61: Определяем, что будет в меню: категории, количество позиций, фирменные хиты, завтраки, сезонные предложения. Опираемся на ассортиментную матрицу и возможности оборудования. Результат: Утверждённая структура меню, по которой шефы пишут рецептуры.
A62: 58 | B62: Меню и продукт | C62: Рецептуры и технологические карты | D62: Шефы и персонал | F62: 46363 | G62: 46409 | H62: =G62-F62+1 | I62: 0 | J62: =IF(I62>=1,"Готово",IF(G62<TODAY(),"Просрочено",IF(F62<=TODAY(),"В работе","В плане"))) | M62: Шефы разрабатывают рецепты и оформляют технологические карты: состав, граммовки, способ приготовления, себестоимость каждой позиции. Результат: На каждую позицию меню есть техкарта с себестоимостью и фото подачи.
A63: 59 | B63: Меню и продукт | C63: Упаковка, печать меню, форма персонала | D63: Команда PECÀN | F63: 46391 | G63: 46423 | H63: =G63-F63+1 | I63: 0 | J63: =IF(I63>=1,"Готово",IF(G63<TODAY(),"Просрочено",IF(F63<=TODAY(),"В работе","В плане"))) | M63: Заказ стаканов, пакетов и коробок, печать меню и ценников, пошив формы. Всё по брендбуку, дизайн стаканов и крафтовых пакетов обновляется. Результат: Упаковка, меню и форма на объекте до технического открытия.
A64: 60 | B64: Меню и продукт | C64: Поставщики сырья: отбор и договоры | D64: Команда PECÀN | F64: 46398 | G64: 46423 | H64: =G64-F64+1 | I64: 0 | J64: =IF(I64>=1,"Готово",IF(G64<TODAY(),"Просрочено",IF(F64<=TODAY(),"В работе","В плане"))) | M64: Выбираем поставщиков кофе, молока, муки, масла и остальных продуктов: сравниваем качество, цены и условия доставки, заключаем договоры. Результат: На каждый ключевой продукт есть основной и запасной поставщик с договором.
A65: 61 | B65: Меню и продукт | C65: Проработки и дегустации на объекте | D65: Шефы и персонал | F65: 46426 | G65: 46431 | H65: =G65-F65+1 | I65: 0 | J65: =IF(I65>=1,"Готово",IF(G65<TODAY(),"Просрочено",IF(F65<=TODAY(),"В работе","В плане"))) | M65: Шефы готовят всё меню на нашем оборудовании, команда PECÀN пробует и даёт правки по вкусу, подаче и времени приготовления. Результат: Каждая позиция утверждена по вкусу и подаче, время отдачи укладывается в стандарт.
A66: 62 | B66: Автоматизация и IT | C66: Закупка касс, принтеров, лицензий iiko | D66: Команда PECÀN | F66: 46398 | G66: 46409 | H66: =G66-F66+1 | I66: 0 | J66: =IF(I66>=1,"Готово",IF(G66<TODAY(),"Просрочено",IF(F66<=TODAY(),"В работе","В плане"))) | M66: Покупка кассовых моноблоков, принтеров чеков и лицензий iiko. Результат: Оборудование и лицензии на руках, можно начинать настройку.
A67: 63 | B67: Автоматизация и IT | C67: Настройка iiko: номенклатура, склады, техкарты | D67: Команда PECÀN | F67: 46412 | G67: 46430 | H67: =G67-F67+1 | I67: 0 | J67: =IF(I67>=1,"Готово",IF(G67<TODAY(),"Просрочено",IF(F67<=TODAY(),"В работе","В плане"))) | M67: Настраиваем систему учёта: заносим меню, склады, техкарты шефов и правила списания продуктов. Результат: Каждая продажа автоматически списывает продукты со склада, остатки видны в системе.
A68: 64 | B68: Автоматизация и IT | C68: Бонусная программа лояльности | D68: Команда PECÀN | F68: 46419 | G68: 46430 | H68: =G68-F68+1 | I68: 0 | J68: =IF(I68>=1,"Готово",IF(G68<TODAY(),"Просрочено",IF(F68<=TODAY(),"В работе","В плане"))) | M68: Настраиваем бонусную программу для гостей и связываем её с кассой, обучаем кассиров. Результат: Гость регистрируется за минуту, бонусы начисляются и списываются на кассе.
A69: 65 | B69: Автоматизация и IT | C69: Kaspi Pay, Webkassa, кассовая зона | D69: Команда PECÀN | F69: 46419 | G69: 46430 | H69: =G69-F69+1 | I69: 0 | J69: =IF(I69>=1,"Готово",IF(G69<TODAY(),"Просрочено",IF(F69<=TODAY(),"В работе","В плане"))) | M69: Подключаем оплату через Kaspi и картой, онлайн-кассу Webkassa, принтеры на баре и кухне. Результат: Тестовая продажа проходит целиком: заказ, оплата, чек, заказ на кухне.
A70: 66 | B70: Автоматизация и IT | C70: Дашборд для владельцев | D70: Команда PECÀN | F70: 46426 | G70: 46437 | H70: =G70-F70+1 | I70: 0 | J70: =IF(I70>=1,"Готово",IF(G70<TODAY(),"Просрочено",IF(F70<=TODAY(),"В работе","В плане"))) | M70: Настраиваем отчёты, которые владельцы видят с телефона: выручка, средний чек, количество гостей, остатки. Результат: Вы открываете приложение и видите выручку за сегодня в реальном времени.
A71: 67 | B71: Автоматизация и IT | C71: Заявки в Wolt, Yandex Eats, Glovo, Choco | D71: Команда PECÀN | F71: 46426 | G71: 46444 | H71: =G71-F71+1 | I71: 0 | J71: =IF(I71>=1,"Готово",IF(G71<TODAY(),"Просрочено",IF(F71<=TODAY(),"В работе","В плане"))) | M71: Готовим меню доставки и подаём заявки на подключение. Решение о подключении принимают сами сервисы. Результат: Заявки поданы во все четыре сервиса, меню и фото готовы.
A72: 68 | B72: Стандарты и обучение | C72: Service Book, должностные инструкции, чек-листы, ХАССП | D72: Команда PECÀN | F72: 46342 | G72: 46374 | H72: =G72-F72+1 | I72: 0 | J72: =IF(I72>=1,"Готово",IF(G72<TODAY(),"Просрочено",IF(F72<=TODAY(),"В работе","В плане"))) | M72: Пишем правила работы кофейни: как встречать гостя и готовить заказ, кто за что отвечает, что делать при открытии и закрытии смены, как соблюдать санитарные нормы. Результат: Комплект документов, по которым новый сотрудник понимает свою работу с первого дня.
A73: 69 | B73: Стандарты и обучение | C73: Обучение управляющего | D73: Команда PECÀN | F73: 46412 | G73: 46423 | H73: =G73-F73+1 | I73: 0 | J73: =IF(I73>=1,"Готово",IF(G73<TODAY(),"Просрочено",IF(F73<=TODAY(),"В работе","В плане"))) | M73: Учим управляющего вести кофейню: графики смен, заказ продуктов, себестоимость, инвентаризация, работа с отзывами и жалобами. Результат: Управляющий самостоятельно составляет график, делает заказ поставщикам и читает отчёты.
A74: 70 | B74: Стандарты и обучение | C74: Договоры ЖКХ, вывоз отходов, уведомление о начале деятельности | D74: Команда PECÀN | F74: 46412 | G74: 46430 | H74: =G74-F74+1 | I74: 0 | J74: =IF(I74>=1,"Готово",IF(G74<TODAY(),"Просрочено",IF(F74<=TODAY(),"В работе","В плане"))) | M74: Договоры на электричество, воду, вывоз мусора и дезинсекцию, уведомление о начале деятельности. Результат: Все договоры подписаны, уведомление подано, можно легально работать.
A75: 71 | B75: Стандарты и обучение | C75: Академия PECÀN: бариста, пекарня, кухня, сервис | D75: Команда PECÀN | E75: Персонал кофейни | F75: 46426 | G75: 46431 | H75: =G75-F75+1 | I75: 0 | J75: =IF(I75>=1,"Готово",IF(G75<TODAY(),"Просрочено",IF(F75<=TODAY(),"В работе","В плане"))) | L75: да | M75: Неделя обучения всей команды: бариста тренируют кофе и скорость, пекари и повара работают по техкартам, зал и касса учат меню и стандарты общения с гостем. Результат: Каждый сотрудник знает меню и свои действия на смене, готов к аттестации.
A76: 72 | B76: Стандарты и обучение | C76: Аттестация команды | D76: Команда PECÀN | F76: 46431 | G76: 46431 | H76: =G76-F76+1 | I76: 0 | J76: =IF(I76>=1,"Готово",IF(G76<TODAY(),"Просрочено",IF(F76<=TODAY(),"В работе","В плане"))) | K76: да | L76: да | M76: Экзамен для каждого сотрудника: теория по меню и стандартам плюс практика на рабочем месте. Результат: К смене допущены только те, кто сдал аттестацию.
A77: 73 | B77: Маркетинг запуска | C77: Медиаплан запуска | D77: Команда PECÀN | F77: 46321 | G77: 46339 | H77: =G77-F77+1 | I77: 0 | J77: =IF(I77>=1,"Готово",IF(G77<TODAY(),"Просрочено",IF(F77<=TODAY(),"В работе","В плане"))) | M77: План продвижения: что, где и когда публикуем до и после открытия, какие активности проводим, какой бюджет на рекламу нужен. Результат: Календарь публикаций и активностей с бюджетом по неделям.
A78: 74 | B78: Маркетинг запуска | C78: Instagram: прогрев до открытия | D78: Команда PECÀN | F78: 46391 | G78: 46459 | H78: =G78-F78+1 | I78: 0 | J78: =IF(I78>=1,"Готово",IF(G78<TODAY(),"Просрочено",IF(F78<=TODAY(),"В работе","В плане"))) | M78: Ведём аккаунт до открытия: показываем ремонт, команду, пробы меню, собираем аудиторию района. Результат: К открытию у аккаунта есть живые подписчики из района, которые ждут запуска.
A79: 75 | B79: Маркетинг запуска | C79: Карточки в 2ГИС, Яндекс и Google | D79: Команда PECÀN | F79: 46419 | G79: 46430 | H79: =G79-F79+1 | I79: 0 | J79: =IF(I79>=1,"Готово",IF(G79<TODAY(),"Просрочено",IF(F79<=TODAY(),"В работе","В плане"))) | M79: Создаём и оформляем карточки заведения на картах: адрес, часы работы, фото, меню. Результат: PECÀN находится в поиске на картах, информация и фото актуальны.
A80: 76 | B80: Маркетинг запуска | C80: Подготовка торжественного открытия | D80: Команда PECÀN | F80: 46433 | G80: 46458 | H80: =G80-F80+1 | I80: 0 | J80: =IF(I80>=1,"Готово",IF(G80<TODAY(),"Просрочено",IF(F80<=TODAY(),"В работе","В плане"))) | M80: Готовим торжественное открытие: программа дня, приглашения блогерам и гостям, подарки, фото и видеосъёмка. Результат: Сценарий утверждён, гости приглашены, всё закуплено за день до события.
A81: 77 | B81: Запуск | C81: Первый закуп продуктов и расходников | D81: Команда PECÀN | F81: 46428 | G81: 46432 | H81: =G81-F81+1 | I81: 0 | J81: =IF(I81>=1,"Готово",IF(G81<TODAY(),"Просрочено",IF(F81<=TODAY(),"В работе","В плане"))) | M81: Первая закупка продуктов, кофе, молока, упаковки и расходников под стартовое меню. Результат: Склад заполнен на первую неделю работы.
A82: 78 | B82: Запуск | C82: Техническое открытие | D82: Команда PECÀN | E82: Все участники | F82: 46433 | G82: 46433 | H82: =G82-F82+1 | I82: 0 | J82: =IF(I82>=1,"Готово",IF(G82<TODAY(),"Просрочено",IF(F82<=TODAY(),"В работе","В плане"))) | K82: да | L82: да | M82: Первый рабочий день без рекламы и вывески о запуске. Принимаем первых гостей и проверяем все процессы в реальной работе. Результат: Кофейня открыла двери и отработала полную смену.
A83: 79 | B83: Запуск | C83: Тестовая эксплуатация, 10 дней | D83: Команда PECÀN | E83: Персонал кофейни | F83: 46433 | G83: 46442 | H83: =G83-F83+1 | I83: 0 | J83: =IF(I83>=1,"Готово",IF(G83<TODAY(),"Просрочено",IF(F83<=TODAY(),"В работе","В плане"))) | L83: да | M83: Десять дней работаем в тихом режиме: закрытая фокус-группа, друзья и соседи. Замеряем скорость отдачи, собираем отзывы, находим узкие места. Результат: Список проблем найден и устранён, заказ отдаётся за стандартное время даже в пик.
A84: 80 | B84: Запуск | C84: Работа в мягком режиме, доводка процессов | D84: Шефы и персонал | F84: 46443 | G84: 46458 | H84: =G84-F84+1 | I84: 0 | J84: =IF(I84>=1,"Готово",IF(G84<TODAY(),"Просрочено",IF(F84<=TODAY(),"В работе","В плане"))) | M84: Работаем для всех, но без громкой рекламы. Команда набирает скорость, докручиваем меню и процессы по отзывам гостей. Результат: Команда уверенно проходит пиковые часы, отзывы на картах положительные.
A85: 81 | B85: Запуск | C85: Торжественное открытие | D85: Команда PECÀN | E85: Все участники | F85: 46459 | G85: 46459 | H85: =G85-F85+1 | I85: 0 | J85: =IF(I85>=1,"Готово",IF(G85<TODAY(),"Просрочено",IF(F85<=TODAY(),"В работе","В плане"))) | K85: да | L85: да | M85: Официальное открытие PECÀN с гостями, блогерами и праздничной программой. Результат: Праздник прошёл, о PECÀN узнал район, первые публикации вышли.
A86: 82 | B86: Запуск | C86: Итоговый аудит и акт, передача кофейни владельцам | D86: Команда PECÀN | F86: 46461 | G86: 46465 | H86: =G86-F86+1 | I86: 0 | J86: =IF(I86>=1,"Готово",IF(G86<TODAY(),"Просрочено",IF(F86<=TODAY(),"В работе","В плане"))) | M86: Проверяем работу кофейни после открытия, передаём все документы, доступы и контакты, подписываем итоговый акт. Результат: Кофейня работает самостоятельно, у владельцев есть все документы и доступы.

Sheet Вехи
A1: Вехи
A2: Контрольные точки проекта
A4: Дата | B4: Веха | C4: Ответственный | D4: Отметка | E4: Критический путь | F4: Осталось дней | G4: Условие и детали
A5: 46292 | B5: Договор подписан | C5: Команда PECÀN | F5: =A5-TODAY() | G5: Подписание договора на сопровождение открытия кофейни-пекарни. С этой даты идёт отсчёт всех работ.
A6: 46313 | B6: Зонирование согласовано | C6: Команда PECÀN | E6: да | F6: =A6-TODAY() | G6: Выбор одного варианта планировки из предложенных. От него зависят проект ТХ, дизайн и работа строителей.
A7: 46315 | B7: Защита финмодели и бюджета | C7: Команда PECÀN | F7: =A7-TODAY() | G7: Встреча, на которой проходим финансовую модель и бюджет открытия: откуда каждая цифра и где можно сэкономить.
A8: 46325 | B8: Договор подряда подписан | C8: Команда PECÀN | E8: да | F8: =A8-TODAY() | G8: Подписание договора подряда с выбранной бригадой. В договоре: сроки по этому графику, поэтапная оплата, закупка материалов по проектной смете.
A9: 46325 | B9: Договоры на услуги по дизайну подписаны | C9: Команда PECÀN | E9: да | F9: =A9-TODAY() | G9: Договоры с выбранными исполнителями: рабочая документация, свет и розетки, вывеска, авторский надзор. В договорах фиксируются даты сдачи и оплата по этапам.
A10: 46328 | B10: Раздел ТХ и задание на инженерные сети сданы | C10: Команда PECÀN | F10: =A10-TODAY() | G10: Передача готового раздела ТХ и задания на инженерные сети. С этого момента строители могут выходить на объект и делать рабочие схемы.
A11: 46328 | B11: Строители вышли на объект | C11: Строители | F11: =A11-TODAY() | G11: Начало ремонта: бригада заходит на объект с материалами и инструментом.
A12: 46346 | B12: Спецификации и бюджет закупок утверждены | C12: Команда PECÀN | E12: да | F12: =A12-TODAY() | G12: Утверждение списка закупок и суммы, которую готовы на них потратить.
A13: 46346 | B13: Дизайн-проект готов полностью | C13: Команда PECÀN | E13: да | F13: =A13-TODAY() | G13: Сдача всего дизайн-проекта: концепция, визуализации, рабочая документация. Он должен быть готов до поездки в Китай, потому что по нему закупаются мебель и свет.
A14: 46412 | B14: Приёмка строительной готовности | C14: Команда PECÀN | F14: =A14-TODAY() | G14: Совместный обход помещения после ремонта: команда PECÀN, строители, дизайнер. Проверяем качество работ и готовность принять оборудование.
A15: 46416 | B15: Штат укомплектован: 10–14 человек | C15: Команда PECÀN | F15: =A15-TODAY() | G15: Финальная проверка: все должности закрыты, люди подтвердили выход.
A16: 46416 | B16: Оборудование и мебель на объекте | C16: Поставщики и логистика | E16: да | F16: =A16-TODAY() | G16: Разгрузка и приёмка: пересчитываем места, проверяем целостность упаковки и комплектность.
A17: 46427 | B17: Интерьер принят дизайнером по проекту | C17: Подрядчики по дизайну | F17: =A17-TODAY() | G17: Финальный обход помещения с дизайнером после расстановки мебели и декора.
A18: 46431 | B18: Аттестация команды | C18: Команда PECÀN | E18: да | F18: =A18-TODAY() | G18: Экзамен для каждого сотрудника: теория по меню и стандартам плюс практика на рабочем месте.
A19: 46433 | B19: Техническое открытие | C19: Команда PECÀN | E19: да | F19: =A19-TODAY() | G19: Первый рабочий день без рекламы и вывески о запуске. Принимаем первых гостей и проверяем все процессы в реальной работе.
A20: 46459 | B20: Торжественное открытие | C20: Команда PECÀN | E20: да | F20: =A20-TODAY() | G20: Официальное открытие PECÀN с гостями, блогерами и праздничной программой.
A22: На чём держится график
A23: Проектная документация дизайна готова полностью до выезда в Китай: по ней собираются закупочные спецификации.
A24: Фабричные заказы отгружаются до Китайского Нового года (6 февраля 2027). Опоздание сдвигает открытие на 3–4 недели.
A25: Сроки доставки и таможни зависят от перевозчика и терминалов на границе. После прибытия груза на монтаж и пусконаладку нужно до 14 дней.
A26: Материалы согласуются за 3 рабочих дня. Каждый день задержки согласования сдвигает зависимые работы.
A27: Торжественное открытие назначено на субботу после Ораза айта и до Наурыза. Дату уточняем в январе.

Sheet Роли
A1: Роли и зоны ответственности
A2: Цвет роли совпадает с цветом полос на листе «График»
A4: Роль | B4: Кто | C4: Задач в плане | D4: Зона ответственности
A5: Команда PECÀN | B5: Основатели и Gastro Ultima | C5: =COUNTIF('График'!D:D,A5) | D5: • Ведёт проект целиком: график, решения, согласования, бюджет • Аналитика локации, финансовая модель, маркетинговая стратегия • Технологический проект, задание на инженерные сети, технологический надзор • Концепция интерьера и 3D-визуализации, выбор подрядчиков по дизайну и строительной бригады • Спецификации, выездная сессия в Китае, оплата оборудования и логистики • Юрлицо, счёт, договоры с ЖКХ и поставщиками сырья • Подбор команды, обучение, аттестация • iiko, лояльность, стандарты, ХАССП, запуск и открытие
A6: Подрядчики по дизайну | B6: Точечные услуги · выбираем до 30 октября | C6: =COUNTIF('График'!D:D,A6) | D6: • Рабочие чертежи для строителей, ведомости отделки и мебели, смета • План освещения, розеток и выключателей • Эскиз фасадной вывески • Авторский надзор за отделкой и декором
A7: Строители | B7: Новая бригада · выбираем до 30 октября | C7: =COUNTIF('График'!D:D,A7) | D7: • Черновые работы и перегородки по проекту • Рабочие схемы сетей с расчётами • Электрика 380 В, вода, канализация, трапы, жироуловитель • Вентиляция и кондиционирование • Чистовая отделка, свет, сантехника • Сдача помещения по акту строительной готовности
A8: Поставщики и логистика | B8: Фабрики КНР, дилер кофемашины, карго, таможня | C8: =COUNTIF('График'!D:D,A8) | D8: • Производство оборудования, мебели, света, посуды • Поставка кофемашины от дилера в Казахстане • Отгрузка до Китайского Нового года • Доставка, таможенное оформление, разгрузка на объекте
A9: Шефы и персонал | B9: Шеф-пекарь, шеф-бариста, управляющий, линейный персонал | C9: =COUNTIF('График'!D:D,A9) | D9: • Рецептуры и технологические карты • Проработки и дегустации меню • Обучение в Академии PECÀN и аттестация • Работа смен в тестовом режиме и на открытии
